odoo/addons/request_document_expense/README.rst
odoo/addons/request_document_expense/__init__.py
odoo/addons/request_document_expense/__manifest__.py
odoo/addons/request_document_expense/i18n/request_document_expense.pot
odoo/addons/request_document_expense/models/__init__.py
odoo/addons/request_document_expense/models/hr_expense.py
odoo/addons/request_document_expense/models/request_document.py
odoo/addons/request_document_expense/models/request_order.py
odoo/addons/request_document_expense/models/res_company.py
odoo/addons/request_document_expense/models/res_config_settings.py
odoo/addons/request_document_expense/readme/CONTRIBUTORS.rst
odoo/addons/request_document_expense/readme/DESCRIPTION.rst
odoo/addons/request_document_expense/static/description/icon.png
odoo/addons/request_document_expense/static/description/index.html
odoo/addons/request_document_expense/tests/__init__.py
odoo/addons/request_document_expense/tests/test_request_document.py
odoo/addons/request_document_expense/views/hr_expense_views.xml
odoo/addons/request_document_expense/views/request_order_view.xml
odoo/addons/request_document_expense/views/res_config_settings_views.xml
odoo_addon_request_document_expense-18.0.1.0.5.dist-info/METADATA
odoo_addon_request_document_expense-18.0.1.0.5.dist-info/WHEEL
odoo_addon_request_document_expense-18.0.1.0.5.dist-info/top_level.txt
odoo_addon_request_document_expense-18.0.1.0.5.dist-info/RECORD
